btsdp/__init__.py
btsdp/client.py
btsdp/fuzz.py
btsdp/sdp.py
btsdp/server.py
btsdp/svc_attrs.py
btsdp/svc_cls.py
btsdp/pytransform/__init__.py
btsdp/pytransform/platforms/linux/aarch64/_pytransform.so
btsdp/pytransform/platforms/linux/x86_64/_pytransform.so
btsdp-0.0.8.dist-info/LICENSE.txt
btsdp-0.0.8.dist-info/METADATA
btsdp-0.0.8.dist-info/WHEEL
btsdp-0.0.8.dist-info/top_level.txt
btsdp-0.0.8.dist-info/RECORD
