Metadata-Version: 2.1
Name: btsdp
Version: 0.0.8
Summary: Bluetooth SDP Utilities
Home-page: https://pypi.org/project/btsdp
Author: Cibo
Author-email: cibo@bio-electric.com
License: Proprietary
Classifier: Operating System :: POSIX :: Linux
Classifier: Programming Language :: Python :: 3
Classifier: Programming Language :: Python :: 3 :: Only
Classifier: Programming Language :: Python :: 3.10
Classifier: License :: Other/Proprietary License
Requires-Python: ==3.10.*
License-File: LICENSE.txt
Requires-Dist: bthci (>=0.0.39)
Requires-Dist: xpycommon (>=0.0.19)
